minify_simple/__init__.py
minify_simple/cli.py
minify_simple/exceptions.py
minify_simple/minify.py
minify_simple-0.3.0.dist-info/METADATA
minify_simple-0.3.0.dist-info/WHEEL
minify_simple-0.3.0.dist-info/entry_points.txt
minify_simple-0.3.0.dist-info/licenses/LICENSE
minify_simple-0.3.0.dist-info/RECORD
