Metadata-Version: 2.4
Name: minify-simple
Version: 0.3.0
Summary: Minificador de archivos web: js, css, html
Project-URL: Homepage, https://git.disroot.org/devsol/minify-simple
Project-URL: Issues, https://git.disroot.org/devsol/minify-simple/issues
Author-email: Alexis Torres <devsol@tutamail.com>
License-Expression: MIT
License-File: LICENSE
Classifier: Environment :: Web Environment
Classifier: Operating System :: OS Independent
Classifier: Programming Language :: Python :: 3
Classifier: Topic :: Text Editors :: Integrated Development Environments (IDE)
Requires-Python: >=3.10
Requires-Dist: minify-html==0.16.4
Requires-Dist: rich==14.0.0
